CHANGELOG.md
LICENSE.txt
MANIFEST.in
README.md
setup.py
doc/source/api.rst
doc/source/applications.rst
doc/source/axis.rst
doc/source/backups.rst
doc/source/communication.rst
doc/source/conf.py
doc/source/controller.rst
doc/source/fwversion.rst
doc/source/index.rst
doc/source/low_level_methods.rst
doc/source/programming.rst
doc/source/utils.rst
doc/source/_static/ALBALogo_WHITE.png
doc/source/_static/IcePAP_3D.png
icepap/__init__.py
icepap/axis.py
icepap/communication.py
icepap/controller.py
icepap/fwversion.py
icepap/group.py
icepap/simulator.py
icepap/tcp.py
icepap/utils.py
icepap/vdatalib.py
icepap.egg-info/PKG-INFO
icepap.egg-info/SOURCES.txt
icepap.egg-info/dependency_links.txt
icepap.egg-info/entry_points.txt
icepap.egg-info/requires.txt
icepap.egg-info/top_level.txt
icepap/cli/__init__.py
icepap/cli/__main__.py
icepap/cli/cli.py
icepap/cli/progress_bar.py
icepap/cli/repl.py
icepap/cli/tables.py
icepap/cli/utils.py
tests/test_cli.py
tests/test_group.py
tests/test_icepap.py