Metadata-Version: 2.1
Name: icepap
Version: 3.12.0
Summary: Python IcePAP Extension
Home-page: https://github.com/ALBA-Synchrotron/pyIcePAP
Author: Guifre Cuni et al.
Author-email: ctbeamlines@cells.es
License: GPLv3
Classifier: Development Status :: 5 - Production/Stable
Classifier: Intended Audience :: Developers
Classifier: Intended Audience :: End Users/Desktop
Classifier: License :: OSI Approved :: GNU General Public License v3 (GPLv3)
Classifier: Natural Language :: English
Classifier: Operating System :: POSIX
Classifier: Operating System :: Microsoft :: Windows
Classifier: Programming Language :: Python :: 3.5
Classifier: Topic :: Communications
Classifier: Topic :: Software Development :: Libraries
Requires-Python: >=3.5
License-File: LICENSE.txt
Requires-Dist: numpy
Requires-Dist: click<8; python_version < "3.6"
Requires-Dist: click>=7; python_version >= "3.6"
Requires-Dist: prompt_toolkit>=3; python_version >= "3.6"
Requires-Dist: beautifultable>=1; python_version >= "3.6"
Provides-Extra: simulator
Requires-Dist: sinstruments>=1.3; extra == "simulator"
Requires-Dist: motorlib>=0.1; extra == "simulator"
